LICENSE
MANIFEST.in
README.rst
requirements.txt
setup.py
livingbio_newspaper.egg-info/PKG-INFO
livingbio_newspaper.egg-info/SOURCES.txt
livingbio_newspaper.egg-info/dependency_links.txt
livingbio_newspaper.egg-info/not-zip-safe
livingbio_newspaper.egg-info/requires.txt
livingbio_newspaper.egg-info/top_level.txt
newspaper/__init__.py
newspaper/api.py
newspaper/article.py
newspaper/cleaners.py
newspaper/configuration.py
newspaper/extractors.py
newspaper/images.py
newspaper/mthreading.py
newspaper/network.py
newspaper/nlp.py
newspaper/outputformatters.py
newspaper/parsers.py
newspaper/settings.py
newspaper/source.py
newspaper/text.py
newspaper/urls.py
newspaper/utils.py
newspaper/version.py
newspaper/resources/images/known-image-css.txt
newspaper/resources/misc/google_sources.txt
newspaper/resources/misc/popular_sources.txt
newspaper/resources/misc/stopwords-nlp-en.txt
newspaper/resources/misc/useragents.txt
newspaper/resources/text/stopwords-ar.txt
newspaper/resources/text/stopwords-da.txt
newspaper/resources/text/stopwords-de.txt
newspaper/resources/text/stopwords-en.txt
newspaper/resources/text/stopwords-es.txt
newspaper/resources/text/stopwords-fi.txt
newspaper/resources/text/stopwords-fr.txt
newspaper/resources/text/stopwords-hu.txt
newspaper/resources/text/stopwords-id.txt
newspaper/resources/text/stopwords-it.txt
newspaper/resources/text/stopwords-ko.txt
newspaper/resources/text/stopwords-nb.txt
newspaper/resources/text/stopwords-nl.txt
newspaper/resources/text/stopwords-no.txt
newspaper/resources/text/stopwords-pt.txt
newspaper/resources/text/stopwords-ru.txt
newspaper/resources/text/stopwords-sv.txt
newspaper/resources/text/stopwords-vi.txt
newspaper/resources/text/stopwords-zh.txt
newspaper/videos/__init__.py
newspaper/videos/extractors.py
newspaper/videos/videos.py