Metadata-Version: 1.0
Name: livingbio-newspaper
Version: 1514472980.68
Summary: Simplified python article discovery & extraction.
Home-page: https://github.com/codelucas/newspaper/
Author: Lucas Ou-Yang
Author-email: lucasyangpersonal@gmail.com
License: MIT
Platform: UNKNOWN
